pyscript/__init__.py
pyscript/__main__.py
pyscript/_generator.py
pyscript/cli.py
pyscript/plugins/__init__.py
pyscript/plugins/create.py
pyscript/plugins/hookspecs.py
pyscript/plugins/run.py
pyscript/templates/basic.html
pyscript-0.3.3.dist-info/LICENSE
pyscript-0.3.3.dist-info/METADATA
pyscript-0.3.3.dist-info/WHEEL
pyscript-0.3.3.dist-info/entry_points.txt
pyscript-0.3.3.dist-info/top_level.txt
pyscript-0.3.3.dist-info/RECORD
